{
  "id": 14,
  "name": "tes",
  "slug": "tes",
  "permalink": "https://www.mediamentor.live/wc-test/urun/tes/",
  "date_created": "2023-10-20T23:57:04",
  "date_created_gmt": "2023-10-20T23:57:04",
  "date_modified": "2023-10-20T23:57:05",
  "date_modified_gmt": "2023-10-20T23:57:05",
  "type": "simple",
  "status": "publish",
  "featured": false,
  "catalog_visibility": "visible",
  "description": "<p>test</p>\n",
  "short_description": "<p>asdasdasd</p>\n",
  "sku": "",
  "price": "20",
  "regular_price": "100",
  "sale_price": "20",
  "date_on_sale_from": null,
  "date_on_sale_from_gmt": null,
  "date_on_sale_to": null,
  "date_on_sale_to_gmt": null,
  "on_sale": true,
  "purchasable": true,
  "total_sales": 0,
  "virtual": false,
  "downloadable": false,
  "downloads": [],
  "download_limit": -1,
  "download_expiry": -1,
  "external_url": "",
  "button_text": "",
  "tax_status": "taxable",
  "tax_class": "",
  "manage_stock": false,
  "stock_quantity": null,
  "backorders": "no",
  "backorders_allowed": false,
  "backordered": false,
  "low_stock_amount": null,
  "sold_individually": false,
  "weight": "",
  "dimensions": {
    "length": "",
    "width": "",
    "height": ""
  },
  "shipping_required": true,
  "shipping_taxable": true,
  "shipping_class": "",
  "shipping_class_id": 0,
  "reviews_allowed": true,
  "average_rating": "0.00",
  "rating_count": 0,
  "upsell_ids": [],
  "cross_sell_ids": [],
  "parent_id": 0,
  "purchase_note": "",
  "categories": [
    {
      "id": 15,
      "name": "Genel",
      "slug": "genel"
    }
  ],
  "tags": [],
  "images": [],
  "attributes": [],
  "default_attributes": [],
  "variations": [],
  "grouped_products": [],
  "menu_order": 0,
  "price_html": "<del aria-hidden=\"true\"><span class=\"woocommerce-Price-amount amount\"><bdi><span class=\"woocommerce-Price-currencySymbol\">&#8378;</span>100,00</bdi></span></del> <ins><span class=\"woocommerce-Price-amount amount\"><bdi><span class=\"woocommerce-Price-currencySymbol\">&#8378;</span>20,00</bdi></span></ins>",
  "related_ids": [],
  "meta_data": [],
  "stock_status": "instock",
  "has_options": false,
  "post_password": "",
  "jetpack_sharing_enabled": true,
  "_links": {
    "self": [
      {
        "href": "https://www.mediamentor.live/wc-test/wp-json/wc/v3/products/14"
      }
    ],
    "collection": [
      {
        "href": "https://www.mediamentor.live/wc-test/wp-json/wc/v3/products"
      }
    ]
  }
}
